<?xml version="1.0" encoding="utf-8" ?>
<resources>

  <!--  ar-kwabic (ar-kw) -->
  <resource culture="ar-kw" name="permissionpagetitle" value="AR: Role Permission"></resource>
  <resource culture="ar-kw" name="roleid" value="AR:  Role ID"></resource>
  <resource culture="ar-kw" name="roleidRequired" value="AR: Please provide  Role ID"></resource>
  <resource culture="ar-kw" name="formactionid" value="AR:  Form Action ID"></resource>
  <resource culture="ar-kw" name="formactionidRequired" value="AR: Please provide  Form Action ID"></resource>
  <resource culture="ar-kw" name="appformid" value="AR:  App Form ID"></resource>
  <resource culture="ar-kw" name="appformidRequired" value="AR: Please provide  App Form ID"></resource>
  <resource culture="ar-kw" name="status" value="AR:  Status"></resource>
  <resource culture="ar-kw" name="statusRequired" value="AR: Please provide  Status"></resource>
  <resource culture="ar-kw" name="rolepermissionList" value="AR: View All"></resource>
  <resource culture="ar-kw" name="rolepermissionCreate" value="AR: Create"></resource>
  <resource culture="ar-kw" name="rolepermissionUpdate" value="AR: Update"></resource>
  <resource culture="ar-kw" name="rolepermissionDetails" value="AR: Detail"></resource>

  <!--  ar-kwabic (ar-kw) -->

  <!--  English (en-US) -->
  <resource culture="en-us" name="permissionpagetitle" value="Role Permission"></resource>
  <resource culture="en-us" name="roleid" value=" Role ID"></resource>
  <resource culture="en-us" name="roleidRequired" value="Please provide  Role ID"></resource>
  <resource culture="en-us" name="formactionid" value=" Form Action ID"></resource>
  <resource culture="en-us" name="formactionidRequired" value="Please provide  Form Action ID"></resource>
  <resource culture="en-us" name="appformid" value=" App Form ID"></resource>
  <resource culture="en-us" name="appformidRequired" value="Please provide  App Form ID"></resource>
  <resource culture="en-us" name="status" value=" Status"></resource>
  <resource culture="en-us" name="statusRequired" value="Please provide  Status"></resource>
  <resource culture="en-us" name="rolepermissionList" value="View All"></resource>
  <resource culture="en-us" name="rolepermissionCreate" value="Create"></resource>
  <resource culture="en-us" name="rolepermissionUpdate" value="Update"></resource>
  <resource culture="en-us" name="rolepermissionDetails" value="Detail"></resource>
  <!--  English (en-US) -->



</resources>
